savegreenwavereality/__init__.py
savegreenwavereality/greenwavereality.py
savegreenwavereality-0.6.0.dist-info/LICENSE.txt
savegreenwavereality-0.6.0.dist-info/METADATA
savegreenwavereality-0.6.0.dist-info/WHEEL
savegreenwavereality-0.6.0.dist-info/top_level.txt
savegreenwavereality-0.6.0.dist-info/RECORD
