Metadata-Version: 2.1
Name: savegreenwavereality
Version: 0.6.0
Summary: Re-upload of David Fiels repo with fixes for TCP light control on Hassio - Control of Greenwave Reality Lights
Home-page: https://github.com/lukewakeford/greenwavereality
Author: David Fiel
Author-email: github@dfiel.com
License: MIT
Platform: UNKNOWN
Requires-Dist: requests
Requires-Dist: xmltodict
Requires-Dist: urllib3
